drctrl/__init__.py
drctrl/cli.py
drctrl/lib/ConfigParser.py
drctrl/lib/Exceptions.py
drctrl/lib/Project.py
drctrl/lib/Utils.py
drctrl/lib/Validator.py
drctrl/lib/__init__.py
drctrl/lib/rsdf.py
drctrl/lib/schema/base_schema.yml
drctrl/lib/schema/project_id_is_supplied.yml
drctrl/plugins/__init__.py
drctrl/plugins/base.py
drctrl/plugins/input_file.py
drctrl/plugins/input_redshift.py
drctrl/plugins/input_url.py
drctrl/plugins/output_file.py
drctrl/plugins/output_redshift.py
drctrl-0.1.1.dist-info/METADATA
drctrl-0.1.1.dist-info/RECORD
drctrl-0.1.1.dist-info/WHEEL
drctrl-0.1.1.dist-info/entry_points.txt
drctrl-0.1.1.dist-info/top_level.txt
