Metadata-Version: 2.1
Name: drctrl
Version: 0.1.1
Summary: Automatically configuration tool for DataRobot.
Home-page: https://github.com/recruit-tech/drctrl
Author: e-mon
Author-email: emon18@icloud.com
License: UNKNOWN
Platform: UNKNOWN
Classifier: Programming Language :: Python
Classifier: Programming Language :: Python :: 3
Classifier: Environment :: Web Environment
Classifier: Intended Audience :: Developers
Classifier: License :: OSI Approved :: MIT License
Classifier: Operating System :: OS Independent
Classifier: Operating System :: MacOS :: MacOS X
Classifier: Topic :: Software Development :: Libraries :: Python Modules
Requires-Dist: boto3 (==1.9.27)
Requires-Dist: botocore (==1.12.27)
Requires-Dist: certifi (==2018.10.15)
Requires-Dist: chardet (==3.0.4)
Requires-Dist: click (==6.7)
Requires-Dist: datarobot (==2.6.2)
Requires-Dist: docopt (==0.6.2)
Requires-Dist: docutils (==0.14)
Requires-Dist: idna (==2.7)
Requires-Dist: jinja2 (==2.10)
Requires-Dist: jmespath (==0.9.3)
Requires-Dist: markupsafe (==1.0)
Requires-Dist: numpy (==1.15.2)
Requires-Dist: pandas (==0.23.4)
Requires-Dist: pyaml (==17.12.1)
Requires-Dist: pykwalify (==1.7.0)
Requires-Dist: python-dateutil (==2.7.3)
Requires-Dist: pytz (==2018.5)
Requires-Dist: pyyaml (==3.13)
Requires-Dist: requests-toolbelt (==0.8.0)
Requires-Dist: requests (==2.20.0)
Requires-Dist: s3transfer (==0.1.13)
Requires-Dist: scikit-learn (==0.20.0)
Requires-Dist: scipy (==1.1.0)
Requires-Dist: six (==1.11.0)
Requires-Dist: sklearn (==0.0)
Requires-Dist: sqlalchemy (==1.2.12)
Requires-Dist: style (==1.1.0)
Requires-Dist: trafaret (==1.0.2)
Requires-Dist: update (==0.0.1)
Requires-Dist: urllib3 (==1.23)
